pydantic_computed/__init__.py
pydantic_computed/decorator.py
pydantic_computed/types.py
pydantic_computed-0.2.1.dist-info/LICENSE
pydantic_computed-0.2.1.dist-info/METADATA
pydantic_computed-0.2.1.dist-info/WHEEL
pydantic_computed-0.2.1.dist-info/RECORD
